LICENSE
MANIFEST.in
README.rst
THANKS
changelog.rst
setup.py
tests.py
asyncpg/__init__.py
asyncpg/base.py
asyncpg/connection.py
asyncpg/exceptions.py
asyncpg/pool.py
docs/Makefile
docs/api.rst
docs/changelog.rst
docs/conf.py
docs/index.rst
docs/installation.rst
docs/make.bat
docs/tutorial.rst
examples/gen_example.py
tornado_async_pg.egg-info/PKG-INFO
tornado_async_pg.egg-info/SOURCES.txt
tornado_async_pg.egg-info/dependency_links.txt
tornado_async_pg.egg-info/requires.txt
tornado_async_pg.egg-info/top_level.txt