Metadata-Version: 1.1
Name: tornado-async-pg
Version: 0.0.5
Summary: Async postgresql for Tornado.
Home-page: UNKNOWN
Author: ZhouQi(Thanks Frank Smit & Zaar Hai 's Momoko)
Author-email: bitwolaiye@gmail.com
License: MIT
Platform: UNKNOWN
Classifier: Development Status :: 5 - Production/Stable
Classifier: Intended Audience :: Developers
Classifier: License :: OSI Approved :: MIT License
Classifier: Programming Language :: Python :: Implementation :: PyPy
Classifier: Programming Language :: Python :: Implementation :: CPython
Classifier: Programming Language :: Python :: 2.6
Classifier: Programming Language :: Python :: 2.7
Classifier: Programming Language :: Python :: 3.2
Classifier: Programming Language :: Python :: 3.3
Classifier: Programming Language :: Python :: 3.4
Classifier: Topic :: Database
Classifier: Topic :: Database :: Front-Ends
